datalad_dataverse/__init__.py
datalad_dataverse/_version.py
datalad_dataverse/add_sibling_dataverse.py
datalad_dataverse/baseremote.py
datalad_dataverse/conftest.py
datalad_dataverse/dataset.py
datalad_dataverse/remote.py
datalad_dataverse/utils.py
datalad_dataverse/.idea/workspace.xml
datalad_dataverse/tests/__init__.py
datalad_dataverse/tests/fixtures.py
datalad_dataverse/tests/test_add_sibling_dataverse.py
datalad_dataverse/tests/test_dataset.py
datalad_dataverse/tests/test_pydataverse.py
datalad_dataverse/tests/test_register.py
datalad_dataverse/tests/test_remote.py
datalad_dataverse/tests/test_remote_xdlra.py
datalad_dataverse/tests/test_utils.py
datalad_dataverse/tests/utils.py
datalad_dataverse-1.0.3.dist-info/LICENSE
datalad_dataverse-1.0.3.dist-info/METADATA
datalad_dataverse-1.0.3.dist-info/WHEEL
datalad_dataverse-1.0.3.dist-info/entry_points.txt
datalad_dataverse-1.0.3.dist-info/top_level.txt
datalad_dataverse-1.0.3.dist-info/RECORD
