Metadata-Version: 2.1
Name: datalad_dataverse
Version: 1.0.3
Summary: DataLad extension to deposit datasets on Dataverse
Home-page: https://github.com/datalad/datalad-dataverse
Author: The DataLad Team and Contributors
Author-email: team@datalad.org
License: MIT
Classifier: Programming Language :: Python
Classifier: License :: OSI Approved :: MIT License
Classifier: Programming Language :: Python :: 3
Requires-Python: >=3.7
License-File: LICENSE
Requires-Dist: datalad-next >=1.0.0b2
Requires-Dist: datalad >=0.18.0
Requires-Dist: pydataverse >=0.3.4
Requires-Dist: looseversion
Provides-Extra: devel
Requires-Dist: pytest ; extra == 'devel'
Requires-Dist: coverage ; extra == 'devel'
